README.md
setup.py
flexes_feed/__init__.py
flexes_feed/config.py
flexes_feed/scraper.py
flexes_feed/subscriber.py
flexes_feed.egg-info/PKG-INFO
flexes_feed.egg-info/SOURCES.txt
flexes_feed.egg-info/dependency_links.txt
flexes_feed.egg-info/requires.txt
flexes_feed.egg-info/top_level.txt
test/test_scraper.py
test/test_subscriber.py