Metadata-Version: 2.1
Name: flexes-feed
Version: 0.1.0
Summary: Library for setting up data processing pipelines from remote data feeds
Home-page: UNKNOWN
Author: James Arnold
License: UNKNOWN
Platform: UNKNOWN
Classifier: Programming Language :: Python :: 3
Classifier: License :: OSI Approved :: BSD License
Classifier: Operating System :: OS Independent
Provides-Extra: dev
